[
    {
        "mentor_id": 1,
        "mentor_name": "John Doe",
        "mentee_count": 20
    },
    {
        "mentor_id": 2,
        "mentor_name": "Jane Smith",
        "mentee_count": 18
    },
    {
        "mentor_id": 3,
        "mentor_name": "Mike Johnson",
        "mentee_count": 15
    },
    {
        "mentor_id": 4,
        "mentor_name": "Emily Davis",
        "mentee_count": 22
    },
    {
        "mentor_id": 5,
        "mentor_name": "William Brown",
        "mentee_count": 17
    },
    {
        "mentor_id": 6,
        "mentor_name": "Sophia Wilson",
        "mentee_count": 19
    },
    {
        "mentor_id": 7,
        "mentor_name": "James Taylor",
        "mentee_count": 14
    },
    {
        "mentor_id": 8,
        "mentor_name": "Olivia Martinez",
        "mentee_count": 16
    },
    {
        "mentor_id": 9,
        "mentor_name": "David Anderson",
        "mentee_count": 13
    },
    {
        "mentor_id": 10,
        "mentor_name": "Mia Rodriguez",
        "mentee_count": 12
    }
]